reddit_tts_bot/__init__.py
reddit_tts_bot/narrative.py
reddit_tts_bot/tts.py
reddit_tts_bot/video.py
reddit_tts_bot-1.0.7.dist-info/LICENSE
reddit_tts_bot-1.0.7.dist-info/METADATA
reddit_tts_bot-1.0.7.dist-info/WHEEL
reddit_tts_bot-1.0.7.dist-info/top_level.txt
reddit_tts_bot-1.0.7.dist-info/RECORD
