Metadata-Version: 2.1
Name: reddit_tts_bot
Version: 1.0.7
Summary: A module that facilitates the creation of short form content from Reddit posts.
Home-page: https://github.com/jacksoneshbaugh/reddit-tts-bot
Author: Jackson Eshbaugh
Author-email: jacksoneshbaugh@gmail.com
Classifier: Programming Language :: Python :: 3
Classifier: License :: OSI Approved :: GNU General Public License v3 (GPLv3)
Classifier: Operating System :: OS Independent
Requires-Python: >=3.6
License-File: LICENSE
Requires-Dist: attrs >=23.2.0
Requires-Dist: beautifulsoup4 >=4.12.3
Requires-Dist: bs4 >=0.0.2
Requires-Dist: cachetools >=5.3.3
Requires-Dist: certifi >=2024.2.2
Requires-Dist: cffi >=1.16.0
Requires-Dist: charset-normalizer >=3.3.2
Requires-Dist: click >=8.1.7
Requires-Dist: decorator >=4.4.2
Requires-Dist: filelock >=3.14.0
Requires-Dist: fsspec >=2024.5.0
Requires-Dist: gTTS >=2.5.1
Requires-Dist: h11 >=0.14.0
Requires-Dist: idna >=3.7
Requires-Dist: imageio >=2.34.1
Requires-Dist: imageio-ffmpeg >=0.4.9
Requires-Dist: Jinja2 >=3.1.4
Requires-Dist: joblib >=1.4.2
Requires-Dist: llvmlite >=0.42.0
Requires-Dist: MarkupSafe >=2.1.5
Requires-Dist: more-itertools >=10.2.0
Requires-Dist: moviepy >=1.0.3
Requires-Dist: mpmath >=1.3.0
Requires-Dist: networkx >=3.3
Requires-Dist: nltk >=3.8.1
Requires-Dist: numba >=0.59.1
Requires-Dist: numpy >=1.26.4
Requires-Dist: openai-whisper >=20231117
Requires-Dist: opencv-python >=4.9.0.80
Requires-Dist: outcome >=1.3.0.post0
Requires-Dist: pandas >=2.2.2
Requires-Dist: pedalboard >=0.9.6
Requires-Dist: pillow >=10.3.0
Requires-Dist: proglog >=0.1.10
Requires-Dist: pycparser >=2.22
Requires-Dist: pydub >=0.25.1
Requires-Dist: PySocks >=1.7.1
Requires-Dist: python-dateutil >=2.9.0.post0
Requires-Dist: pytz >=2024.1
Requires-Dist: regex >=2024.5.15
Requires-Dist: requests >=2.32.2
Requires-Dist: scipy >=1.13.0
Requires-Dist: selenium >=4.21.0
Requires-Dist: six >=1.16.0
Requires-Dist: sniffio >=1.3.1
Requires-Dist: sortedcontainers >=2.4.0
Requires-Dist: sounddevice >=0.4.6
Requires-Dist: soupsieve >=2.5
Requires-Dist: sympy >=1.12
Requires-Dist: tiktoken >=0.7.0
Requires-Dist: torch >=2.3.0
Requires-Dist: tqdm >=4.66.4
Requires-Dist: trio >=0.25.1
Requires-Dist: trio-websocket >=0.11.1
Requires-Dist: typing-extensions >=4.11.0
Requires-Dist: tzdata >=2024.1
Requires-Dist: urllib3 >=2.2.1
Requires-Dist: voicebox-tts >=0.0.7
Requires-Dist: wsproto >=1.2.0
